audit_log/__init__.py
audit_log/decorators.py
audit_log/middleware.py
audit_log/registration.py
audit_log/models/__init__.py
audit_log/models/fields.py
audit_log/models/managers.py
audit_log/tests/__init__.py
audit_log/tests/runtests.py
audit_log/tests/runtests_custom_auth.py
audit_log/tests/urls.py
audit_log/tests/audit_log_tests/__init__.py
audit_log/tests/audit_log_tests/models.py
audit_log/tests/audit_log_tests/test_logging.py
audit_log/tests/audit_log_tests/test_manager.py
audit_log/tests/audit_log_tests/views.py
django_audit_log-0.7.0.dist-info/DESCRIPTION.rst
django_audit_log-0.7.0.dist-info/METADATA
django_audit_log-0.7.0.dist-info/metadata.json
django_audit_log-0.7.0.dist-info/RECORD
django_audit_log-0.7.0.dist-info/top_level.txt
django_audit_log-0.7.0.dist-info/WHEEL
