Metadata-Version: 1.1
Name: django-audit-log
Version: 0.7.0
Summary: Audit trail for django models
Home-page: https://github.com/Atomidata/django-audit-log
Author: Vasil Vangelovski
Author-email: vvangelovski@gmail.com
License: New BSD License (http://www.opensource.org/licenses/bsd-license.php)
Download-URL: https://github.com/Atomidata/django-audit-log/downloads
Platform: UNKNOWN
Classifier: Development Status :: 5 - Production/Stable
Classifier: Environment :: Plugins
Classifier: Framework :: Django
Classifier: Intended Audience :: Developers
Classifier: License :: OSI Approved :: BSD License
Classifier: Topic :: Software Development :: Libraries :: Python Modules
Classifier: Programming Language :: Python
Classifier: Programming Language :: Python :: 2.6
Classifier: Programming Language :: Python :: 2.7
Classifier: Programming Language :: Python :: 3
Classifier: Programming Language :: Python :: 3.2
Classifier: Programming Language :: Python :: 3.3
Classifier: Programming Language :: Python :: 3.4
